{
    "created_time": "2020-08-18T07:01:13Z",
    "files": [
        {
            "attachment_folder": "",
            "attachments": [
            ],
            "created_time": "2020-08-18T07:01:24Z",
            "modified_time": "2020-08-21T09:02:42Z",
            "name": "使用.md",
            "tags": [
            ]
        },
        {
            "attachment_folder": "",
            "attachments": [
            ],
            "created_time": "2020-08-18T07:02:54Z",
            "modified_time": "2020-08-18T07:06:58Z",
            "name": "常见问题.md",
            "tags": [
            ]
        }
    ],
    "sub_directories": [
    ],
    "version": "1"
}
