{
    "created_time": "2020-07-08T07:34:00Z",
    "files": [
        {
            "attachment_folder": "",
            "attachments": [
            ],
            "created_time": "2020-07-08T07:34:12Z",
            "modified_time": "2020-07-08T07:37:53Z",
            "name": "安装.md",
            "tags": [
            ]
        },
        {
            "attachment_folder": "",
            "attachments": [
            ],
            "created_time": "2020-07-08T07:34:17Z",
            "modified_time": "2020-07-08T07:41:26Z",
            "name": "使用.md",
            "tags": [
            ]
        }
    ],
    "sub_directories": [
    ],
    "version": "1"
}
